TofeyAI/__init__.py
TofeyAI/cli.py
TofeyAI/main.py
tofeyai-0.2.5.dist-info/licenses/LICENSE
tofeyai-0.2.5.dist-info/METADATA
tofeyai-0.2.5.dist-info/WHEEL
tofeyai-0.2.5.dist-info/top_level.txt
tofeyai-0.2.5.dist-info/RECORD
