Metadata-Version: 2.4
Name: TofeyAI
Version: 0.2.5
Summary: مكتبة ذكاء اصطناعي توفي AI
Author: Tofey
Author-email: techuruk@gmail.com
Classifier: Programming Language :: Python :: 3
Classifier: License :: OSI Approved :: MIT License
Classifier: Operating System :: OS Independent
License-File: LICENSE
Requires-Dist: requests
Dynamic: author
Dynamic: author-email
Dynamic: classifier
Dynamic: license-file
Dynamic: requires-dist
Dynamic: summary
